docs/Makefile
docs/authors.rst
docs/conf.py
docs/history.rst
docs/index.rst
docs/installation.rst
docs/make.bat
docs/modules.rst
docs/phenotrex.cli.rst
docs/phenotrex.io.rst
docs/phenotrex.ml.clf.rst
docs/phenotrex.ml.rst
docs/phenotrex.rst
docs/phenotrex.structure.rst
docs/phenotrex.transforms.rst
docs/phenotrex.util.rst
docs/readme.rst
docs/usage.rst
docs/_build/html/_static/file.png
docs/_build/html/_static/minus.png
docs/_build/html/_static/plus.png
phenotrex/__init__.py
phenotrex/bin/prodigal.linux
phenotrex/bin/prodigal.osx.10.9.5
phenotrex/bin/prodigal.windows.exe
phenotrex/cli/__init__.py
phenotrex/cli/cccv.py
phenotrex/cli/clf_opt.py
phenotrex/cli/compute_genotype.py
phenotrex/cli/cv.py
phenotrex/cli/generic_func.py
phenotrex/cli/generic_opt.py
phenotrex/cli/get_weights.py
phenotrex/cli/main.py
phenotrex/cli/plot.py
phenotrex/cli/predict.py
phenotrex/cli/train.py
phenotrex/io/__init__.py
phenotrex/io/flat.py
phenotrex/io/serialization.py
phenotrex/ml/__init__.py
phenotrex/ml/cccv.py
phenotrex/ml/feature_select.py
phenotrex/ml/prediction.py
phenotrex/ml/shap_handler.py
phenotrex/ml/trex_classifier.py
phenotrex/ml/clf/__init__.py
phenotrex/ml/clf/svm.py
phenotrex/ml/clf/xgbm.py
phenotrex/structure/__init__.py
phenotrex/structure/records.py
phenotrex/transforms/__init__.py
phenotrex/transforms/annotation.py
phenotrex/transforms/resampling.py
phenotrex/util/__init__.py
phenotrex/util/external_data.py
phenotrex/util/helpers.py
phenotrex/util/logging.py
phenotrex/util/plotting.py
phenotrex/util/taxonomy.py
tests/__init__.py
tests/targets.py
tests/test_ml.py
tests/test_shap_handler.py
tests/test_transforms.py
tests/test_util.py
tests/test_data/flat/T3SS/T3SS.genotype
tests/test_data/flat/T3SS/T3SS.phenotype
tests/test_data/flat/T3SS/T3SS.taxids
tests/test_data/flat/T3SS_trunc/T3SS_trunc.genotype
tests/test_data/flat/T3SS_trunc/T3SS_trunc.phenotype
tests/test_data/flat/T3SS_trunc/T3SS_trunc.taxids
tests/test_data/genomic/GCA_000692775_1_trunc2.faa
phenotrex-0.6.0.dist-info/AUTHORS.rst
phenotrex-0.6.0.dist-info/LICENSE
phenotrex-0.6.0.dist-info/METADATA
phenotrex-0.6.0.dist-info/WHEEL
phenotrex-0.6.0.dist-info/entry_points.txt
phenotrex-0.6.0.dist-info/top_level.txt
phenotrex-0.6.0.dist-info/RECORD
