Metadata-Version: 2.1
Name: phenotrex
Version: 0.6.0
Summary: Microbial Phenotype Prediction
Home-page: https://github.com/univieCUBE/phenotrex
Author: Lukas Lüftinger
Author-email: lukas.lueftinger@outlook.com
License: MIT license
Keywords: phenotrex
Platform: UNKNOWN
Classifier: Development Status :: 2 - Pre-Alpha
Classifier: Intended Audience :: Developers
Classifier: License :: OSI Approved :: MIT License
Classifier: Natural Language :: English
Classifier: Programming Language :: Python :: 3.7
Requires-Dist: scikit-learn (<=0.23.2,>=0.22)
Requires-Dist: numpy (>=1.15)
Requires-Dist: matplotlib (>=3.1.3)
Requires-Dist: xgboost (<=1.3,>=1.0.1)
Requires-Dist: shap (<0.36,>=0.34)
Requires-Dist: click (>=7.0)
Requires-Dist: biopython (<=1.77,>=1.74)
Requires-Dist: tqdm (>=4.26.0)
Requires-Dist: pandas (>=1.0)
Provides-Extra: fasta
Requires-Dist: deepnog (==1.2.2) ; extra == 'fasta'
Requires-Dist: ete3 ; extra == 'fasta'
